README
setup.py
solartime.py
solartime.egg-info/PKG-INFO
solartime.egg-info/SOURCES.txt
solartime.egg-info/dependency_links.txt
solartime.egg-info/requires.txt
solartime.egg-info/top_level.txt