Metadata-Version: 1.1
Name: solartime
Version: 0.1b0
Summary: Calculations for solar time such as dawn, sunrise, sunset, dusk.
Home-page: UNKNOWN
Author: David Riggs
Author-email: driggs@myotisoft.com
License: Apache-2.0
Platform: UNKNOWN
Classifier: Intended Audience :: Developers
Classifier: Programming Language :: Python
Classifier: Programming Language :: Python :: 2.7
Classifier: Programming Language :: Python :: 3
